safeds_stubgen/__init__.py
safeds_stubgen/_helpers.py
safeds_stubgen/api_analyzer/__init__.py
safeds_stubgen/api_analyzer/_api.py
safeds_stubgen/api_analyzer/_ast_visitor.py
safeds_stubgen/api_analyzer/_ast_walker.py
safeds_stubgen/api_analyzer/_get_api.py
safeds_stubgen/api_analyzer/_mypy_helpers.py
safeds_stubgen/api_analyzer/_package_metadata.py
safeds_stubgen/api_analyzer/_types.py
safeds_stubgen/api_analyzer/cli/__init__.py
safeds_stubgen/api_analyzer/cli/_cli.py
safeds_stubgen/docstring_parsing/__init__.py
safeds_stubgen/docstring_parsing/_abstract_docstring_parser.py
safeds_stubgen/docstring_parsing/_create_docstring_parser.py
safeds_stubgen/docstring_parsing/_docstring.py
safeds_stubgen/docstring_parsing/_docstring_parser.py
safeds_stubgen/docstring_parsing/_docstring_style.py
safeds_stubgen/docstring_parsing/_helpers.py
safeds_stubgen/docstring_parsing/_plaintext_docstring_parser.py
safeds_stubgen/main.py
safeds_stubgen/stubs_generator/__init__.py
safeds_stubgen/stubs_generator/_generate_stubs.py
safeds_stubgen/stubs_generator/_helper.py
safeds_stubgen/stubs_generator/_stub_string_generator.py
safe_ds_stubgen-0.3.0.dist-info/LICENSE
safe_ds_stubgen-0.3.0.dist-info/METADATA
safe_ds_stubgen-0.3.0.dist-info/WHEEL
safe_ds_stubgen-0.3.0.dist-info/entry_points.txt
safe_ds_stubgen-0.3.0.dist-info/RECORD
