Metadata-Version: 2.1
Name: safe-ds-stubgen
Version: 0.3.0
Summary: Generation of Safe-DS stubs for Python libraries.
Home-page: https://github.com/Safe-DS/Stub-Generator
License: MIT
Keywords: data-science,machine-learning,dsl
Author: Lars Reimann
Author-email: mail@larsreimann.com
Requires-Python: >=3.11,<4.0
Classifier: License :: OSI Approved :: MIT License
Classifier: Programming Language :: Python :: 3
Classifier: Programming Language :: Python :: 3.11
Classifier: Programming Language :: Python :: 3.12
Requires-Dist: griffe (>=0.42,<0.45)
Requires-Dist: mypy (>=1.6.1,<2.0.0)
Project-URL: Documentation, https://stubgen.readthedocs.io
Project-URL: Repository, https://github.com/Safe-DS/Stub-Generator
